rdSaleOrder/EcsInterface.py
rdSaleOrder/__init__.py
rdSaleOrder/mainModel.py
rdSaleOrder/metadata.py
rdSaleOrder/operation.py
rdSaleOrder/utility.py
tests/__init__.py
tests/test.py
tests/test_demo.py
tests/test_dms_demo.py
tests/test_ecs.py
rdsaleorder-1.0.6.dist-info/METADATA
rdsaleorder-1.0.6.dist-info/WHEEL
rdsaleorder-1.0.6.dist-info/top_level.txt
rdsaleorder-1.0.6.dist-info/RECORD
